data_preprocess/__init__.py
data_preprocess/cangjie_key_map.txt
data_preprocess/ime_keys.py
data_preprocess/keystroke_converter.py
data_preprocess/language_cleaner.py
data_preprocess/typo_generater.py
multilingual_ime/__init__.py
multilingual_ime/candidate.py
multilingual_ime/cli_ime.py
multilingual_ime/core/__init__.py
multilingual_ime/core/custom_decorators.py
multilingual_ime/core/F.py
multilingual_ime/core/multi_job_processing.py
multilingual_ime/deep_models.py
multilingual_ime/ime.py
multilingual_ime/ime_detector.py
multilingual_ime/ime_phase1_train.py
multilingual_ime/key_event_handler.py
multilingual_ime/keystroke_map_db.py
multilingual_ime/keystroke_tokenizer.py
multilingual_ime/multi_config.py
multilingual_ime/phrase_db.py
multilingual_ime/sentence_graph.py
multilingual_ime/src/bopomofo_keystroke_map.db
multilingual_ime/src/cangjie_keystroke_map.db
multilingual_ime/src/chinese_phrase.db
multilingual_ime/src/english_keystroke_map.db
multilingual_ime/src/intact_japanese.txt
multilingual_ime/src/intact_pinyin.txt
multilingual_ime/src/japanese_keystroke_map.db
multilingual_ime/src/keystroke_mapping_dictionary/bopomofo_dict_with_frequency.json
multilingual_ime/src/keystroke_mapping_dictionary/cangjie_dict_with_frequency.json
multilingual_ime/src/keystroke_mapping_dictionary/english_dict_with_frequency.json
multilingual_ime/src/keystroke_mapping_dictionary/phrase_dict_with_frequency.json
multilingual_ime/src/keystroke_mapping_dictionary/pinyin_dict_with_frequency.json
multilingual_ime/src/models/one_hot_dl_token_model_bopomofo_2024-10-27.pth
multilingual_ime/src/models/one_hot_dl_token_model_cangjie_2024-10-27.pth
multilingual_ime/src/models/one_hot_dl_token_model_english_2024-10-27.pth
multilingual_ime/src/models/one_hot_dl_token_model_japanese_2025-03-20.pth
multilingual_ime/src/models/one_hot_dl_token_model_pinyin_2024-10-27.pth
multilingual_ime/src/pinyin_keystroke_map.db
multilingual_ime/src/special_character_keystroke_map.db
multilingual_ime-1.0.0.dist-info/LICENSE.txt
multilingual_ime-1.0.0.dist-info/METADATA
multilingual_ime-1.0.0.dist-info/WHEEL
multilingual_ime-1.0.0.dist-info/RECORD
