Metadata-Version: 2.3
Name: multilingual-ime
Version: 1.0.0
Summary: 
Keywords: IME,Multilingual
Author: JY9150
Author-email: 90738099+JY9150@users.noreply.github.com
Requires-Python: ~=3.13
Classifier: Programming Language :: Python :: 3
Classifier: Programming Language :: Python :: 3.13
Requires-Dist: joblib (>=1.4.2,<2.0.0)
Requires-Dist: keyboard (>=0.13.5,<0.14.0)
Requires-Dist: matplotlib (>=3.9.1,<4.0.0)
Requires-Dist: numpy (>=2.0,<3.0)
Requires-Dist: pypinyin (>=0.52.0,<0.53.0)
Requires-Dist: torch (>=2.7.1,<3.0.0)
Requires-Dist: tqdm (>=4.66.4,<5.0.0)
